LICENSE
MANIFEST.in
README.rst
setup.cfg
setup.py
b2tob3/__init__.py
b2tob3/b2tob3.py
b2tob3.egg-info/PKG-INFO
b2tob3.egg-info/SOURCES.txt
b2tob3.egg-info/dependency_links.txt
b2tob3.egg-info/entry_points.txt
b2tob3.egg-info/top_level.txt
tests/__init__.py
tests/test_replacements.py