Metadata-Version: 1.1
Name: b2tob3
Version: 0.4
Summary: Help migrate HTML files and templates form bootstrap 2 to 3.
Home-page: UNKNOWN
Author: Ramiro Gómez
Author-email: code@ramiro.org
License: Copyright (C) 2013 by Ramiro Gómez (http://ramiro.org/)
